arcsolver/__init__.py
arcsolver/_modidx.py
arcsolver/describe.py
arcsolver/examples.py
arcsolver/ocm.py
arcsolver/ocm_cleaned.py
arcsolver/score.py
arcsolver/solve.py
arcsolver/task.py
arcsolver/utils.py
arcsolver/arc_data/data/evaluation/00576224.json
arcsolver/arc_data/data/evaluation/009d5c81.json
arcsolver/arc_data/data/evaluation/00dbd492.json
arcsolver/arc_data/data/evaluation/03560426.json
arcsolver/arc_data/data/evaluation/05a7bcf2.json
arcsolver/arc_data/data/evaluation/0607ce86.json
arcsolver/arc_data/data/evaluation/0692e18c.json
arcsolver/arc_data/data/evaluation/070dd51e.json
arcsolver/arc_data/data/evaluation/08573cc6.json
arcsolver/arc_data/data/evaluation/0934a4d8.json
arcsolver/arc_data/data/evaluation/09c534e7.json
arcsolver/arc_data/data/evaluation/0a1d4ef5.json
arcsolver/arc_data/data/evaluation/0a2355a6.json
arcsolver/arc_data/data/evaluation/0b17323b.json
arcsolver/arc_data/data/evaluation/0bb8deee.json
arcsolver/arc_data/data/evaluation/0becf7df.json
arcsolver/arc_data/data/evaluation/0c786b71.json
arcsolver/arc_data/data/evaluation/0c9aba6e.json
arcsolver/arc_data/data/evaluation/0d87d2a6.json
arcsolver/arc_data/data/evaluation/0e671a1a.json
arcsolver/arc_data/data/evaluation/0f63c0b9.json
arcsolver/arc_data/data/evaluation/103eff5b.json
arcsolver/arc_data/data/evaluation/11e1fe23.json
arcsolver/arc_data/data/evaluation/12422b43.json
arcsolver/arc_data/data/evaluation/12997ef3.json
arcsolver/arc_data/data/evaluation/12eac192.json
arcsolver/arc_data/data/evaluation/136b0064.json
arcsolver/arc_data/data/evaluation/13713586.json
arcsolver/arc_data/data/evaluation/137f0df0.json
arcsolver/arc_data/data/evaluation/140c817e.json
arcsolver/arc_data/data/evaluation/14754a24.json
arcsolver/arc_data/data/evaluation/15113be4.json
arcsolver/arc_data/data/evaluation/15663ba9.json
arcsolver/arc_data/data/evaluation/15696249.json
arcsolver/arc_data/data/evaluation/16b78196.json
arcsolver/arc_data/data/evaluation/17b80ad2.json
arcsolver-0.0.11.dist-info/LICENSE
arcsolver-0.0.11.dist-info/METADATA
arcsolver-0.0.11.dist-info/WHEEL
arcsolver-0.0.11.dist-info/entry_points.txt
arcsolver-0.0.11.dist-info/top_level.txt
arcsolver-0.0.11.dist-info/RECORD
