Metadata-Version: 2.1
Name: arcsolver
Version: 0.0.11
Summary: A Python library for automatically solving Abstraction and Reasoning Corpus (ARC) challenges using Claude and object-centric modeling.
Home-page: https://github.com/agemoai/arcsolver
Author: Jack Hogan
Author-email: jack@agemo.ai
License: Apache Software License 2.0
Keywords: nbdev jupyter notebook python
Classifier: Development Status :: 4 - Beta
Classifier: Intended Audience :: Developers
Classifier: Natural Language :: English
Classifier: Programming Language :: Python :: 3.7
Classifier: Programming Language :: Python :: 3.8
Classifier: Programming Language :: Python :: 3.9
Classifier: Programming Language :: Python :: 3.10
Classifier: Programming Language :: Python :: 3.11
Classifier: Programming Language :: Python :: 3.12
Classifier: License :: OSI Approved :: Apache Software License
Requires-Python: >=3.7
License-File: LICENSE
Requires-Dist: fastcore
Requires-Dist: numpy
Requires-Dist: scipy
Requires-Dist: pydantic
Requires-Dist: matplotlib
Requires-Dist: nest-asyncio
Requires-Dist: treelib
Provides-Extra: dev
